dstlib
