Metadata-Version: 1.1
Name: dstlib
Version: 1.1
Summary: Data structures python library
Home-page: https://github.com/algebra7/dstlib
Author: Ahmad M Ameen
Author-email: ahmadmameen7@gmail.com
License: UNKNOWN
Platform: UNKNOWN
Classifier: Intended Audience :: Developers
Classifier: License :: OSI Approved :: MIT License
Classifier: Operating System :: OS Independent
Classifier: Programming Language :: Python :: 3
Classifier: Topic :: Software Development :: Libraries :: Python Modules
